[
  {
    "firstName":"Zared",
    "lastName":"Lehemann",
    "email":"zlehemann0@stanford.edu",
    "phone":"728-215-7048",
    "birthday":"12/28/1997",
    "company":"National College of Art and Design",
    "passport":"Norway",
    "destination":"Oslo",
    "familiarFullName":"Zared Lehemann",
    "familiarPhone":"274-102-4107",
    "status":"false",
    "profilePicturePath":"images/1.png"
  },
  {
    "firstName":"Samantha",
    "lastName":"Didball",
    "email":"sdidball1@youtube.com",
    "phone":"556-154-1026",
    "birthday":"3/30/2000",
    "company":"Universidade Moderna de Lisboa",
    "passport":"Portugal",
    "destination":"Sobreira",
    "familiarFullName":"Samantha Didball",
    "familiarPhone":"536-782-1427",
    "status":"false",
    "profilePicturePath":"images/1.png"
  },
  {
    "firstName":"Remus",
    "lastName":"Cherry Holme",
    "email":"rcherry2@xinhuanet.com",
    "phone":"498-530-7103",
    "birthday":"10/30/1997",
    "company":"Lulea University of Technology",
    "passport":"Sweden",
    "destination":"Vetlanda",
    "familiarFullName":"Remus Cherry Holme",
    "familiarPhone":"675-675-5693",
    "status":"false",
    "profilePicturePath":"images/1.png"
  },
  {
    "firstName":"Ida",
    "lastName":"Brend",
    "email":"ibrend3@t-online.de",
    "phone":"794-740-6026",
    "birthday":"8/10/1998",
    "company":"Universitas Lambung Mangkurat",
    "passport":"Indonesia",
    "destination":"Batuidu",
    "familiarFullName":"Ida Brend",
    "familiarPhone":"298-157-3559",
    "status":"false",
    "profilePicturePath":"images/1.png"
  },
  {
    "firstName":"Sherlocke",
    "lastName":"Dudgeon",
    "email":"sdudgeon4@washington.edu",
    "phone":"522-106-4846",
    "birthday":"7/28/1997",
    "company":"Universidad Católica Nuestra Senora de la Asunción",
    "passport":"Paraguay",
    "destination":"Santiago",
    "familiarFullName":"Sherlocke Dudgeon",
    "familiarPhone":"905-773-1209",
    "status":"false",
    "profilePicturePath":"images/1.png"
  },
  {
    "firstName":"Frederigo",
    "lastName":"Labarre",
    "email":"flabarre5@globo.com",
    "phone":"914-109-6712",
    "birthday":"10/23/1997",
    "company":"Polytechnic University of Tirane",
    "passport":"Albania",
    "destination":"Kuçovë",
    "familiarFullName":"Frederigo Labarre",
    "familiarPhone":"715-443-0367",
    "status":"false",
    "profilePicturePath":"images/1.png"
  },
  {
    "firstName":"Mike",
    "lastName":"Duns",
    "email":"mduns6@prweb.com",
    "phone":"927-367-9054",
    "birthday":"1/5/1998",
    "company":"University of Fine Arts Belgrade",
    "passport":"Serbia",
    "destination":"Kučevo",
    "familiarFullName":"Mike Duns",
    "familiarPhone":"199-973-3597",
    "status":"false",
    "profilePicturePath":"images/1.png"
  },
  {
    "firstName":"Nanny",
    "lastName":"Gellan",
    "email":"ngellan7@europa.eu",
    "phone":"429-632-9467",
    "birthday":"1/11/1998",
    "company":"Russian Customs Academy, Vladivostok Branch",
    "passport":"Russia",
    "destination":"Soldato-Aleksandrovskoye",
    "familiarFullName":"Nanny Gellan",
    "familiarPhone":"385-622-3862",
    "status":"false",
    "profilePicturePath":"images/1.png"
  },
  {
    "firstName":"Waite",
    "lastName":"Hebdon",
    "email":"whebdon8@phoca.cz",
    "phone":"265-716-4961",
    "birthday":"6/14/1998",
    "company":"Pontificia Universidad Católica del Perú",
    "passport":"Peru",
    "destination":"Tomepampa",
    "familiarFullName":"Waite Hebdon",
    "familiarPhone":"602-906-4950",
    "status":"false",
    "profilePicturePath":"images/1.png"
  },
  {
    "firstName":"Stoddard",
    "lastName":"Canfer",
    "email":"scanfer9@netscape.com",
    "phone":"922-371-0141",
    "birthday":"9/29/1999",
    "company":"Lulea University of Technology",
    "passport":"Sweden",
    "destination":"Sundsvall",
    "familiarFullName":"Stoddard Canfer",
    "familiarPhone":"451-239-0674",
    "status":"false",
    "profilePicturePath":"images/1.png"
  },
  {
    "firstName":"Fredek",
    "lastName":"Croisier",
    "email":"fcroisiera@elegantthemes.com",
    "phone":"946-537-5438",
    "birthday":"3/3/1998",
    "company":"Huaihua Radio and Television University",
    "passport":"China",
    "destination":"Mayanhe",
    "familiarFullName":"Fredek Croisier",
    "familiarPhone":"694-127-7604",
    "status":"false",
    "profilePicturePath":"images/1.png"
  },
  {
    "firstName":"Corenda",
    "lastName":"Matushevich",
    "email":"cmatushevichb@samsung.com",
    "phone":"275-211-1162",
    "birthday":"1/25/1999",
    "company":"Huaqiao University Quanzhuo",
    "passport":"China",
    "destination":"Huayuan",
    "familiarFullName":"Corenda Matushevich",
    "familiarPhone":"400-481-7402",
    "status":"false",
    "profilePicturePath":"images/1.png"
  },
  {
    "firstName":"Ivar",
    "lastName":"Pley",
    "email":"ipleyc@uol.com.br",
    "phone":"467-812-0183",
    "birthday":"12/16/1997",
    "company":"Universitas Wijaya Kusuma Surabaya",
    "passport":"Indonesia",
    "destination":"Sukolilo",
    "familiarFullName":"Ivar Pley",
    "familiarPhone":"983-923-7255",
    "status":"false",
    "profilePicturePath":"images/1.png"
  },
  {
    "firstName":"Gery",
    "lastName":"Sherbrook",
    "email":"gsherbrookd@oakley.com",
    "phone":"714-809-8120",
    "birthday":"12/21/1998",
    "company":"Higher Technological Institute",
    "passport":"Egypt",
    "destination":"Alexandria",
    "familiarFullName":"Gery Sherbrook",
    "familiarPhone":"741-166-5366",
    "status":"false",
    "profilePicturePath":"images/1.png"
  },
  {
    "firstName":"Virgie",
    "lastName":"Brugh",
    "email":"vbrughe@who.int",
    "phone":"276-551-2078",
    "birthday":"6/4/1998",
    "company":"École de technologie supérieure, Université du Québec",
    "passport":"Canada",
    "destination":"Notre-Dame-des-Prairies",
    "familiarFullName":"Virgie Brugh",
    "familiarPhone":"319-116-8926",
    "status":"false",
    "profilePicturePath":"images/1.png"
  },
  {
    "firstName":"Russ",
    "lastName":"Jansens",
    "email":"rjansensf@statcounter.com",
    "phone":"440-443-4376",
    "birthday":"1/29/1999",
    "company":"Universitas Atma Jaya Yogyakarta",
    "passport":"Indonesia",
    "destination":"Nangahale",
    "familiarFullName":"Russ Jansens",
    "familiarPhone":"713-335-2942",
    "status":"false",
    "profilePicturePath":"images/1.png"
  },
  {
    "firstName":"Brok",
    "lastName":"Unitt",
    "email":"bunittg@slashdot.org",
    "phone":"926-386-4232",
    "birthday":"3/20/1999",
    "company":"Brno University of Technology",
    "passport":"Czech Republic",
    "destination":"Hostomice",
    "familiarFullName":"Brok Unitt",
    "familiarPhone":"636-877-9414",
    "status":"false",
    "profilePicturePath":"images/1.png"
  },
  {
    "firstName":"Doria",
    "lastName":"Pennaman",
    "email":"dpennamanh@miitbeian.gov.cn",
    "phone":"563-189-7303",
    "birthday":"12/8/1997",
    "company":"Technical University of Warsaw",
    "passport":"Poland",
    "destination":"Skórcz",
    "familiarFullName":"Doria Pennaman",
    "familiarPhone":"673-954-8474",
    "status":"false",
    "profilePicturePath":"images/1.png"
  },
  {
    "firstName":"Christean",
    "lastName":"Birney",
    "email":"cbirneyi@berkeley.edu",
    "phone":"980-548-3563",
    "birthday":"11/10/1997",
    "company":"Hanoi University of Science",
    "passport":"Vietnam",
    "destination":"Thành Phố Uông Bí",
    "familiarFullName":"Christean Birney",
    "familiarPhone":"583-802-9986",
    "status":"false",
    "profilePicturePath":"images/1.png"
  },
  {
    "firstName":"Hubey",
    "lastName":"Tutsell",
    "email":"htutsellj@mtv.com",
    "phone":"186-321-1792",
    "birthday":"7/15/1997",
    "company":"Universidade de Guarulhos",
    "passport":"Brazil",
    "destination":"Extremoz",
    "familiarFullName":"Hubey Tutsell",
    "familiarPhone":"763-375-2242",
    "status":"false",
    "profilePicturePath":"images/1.png"
  },
  {
    "firstName":"Abdul",
    "lastName":"Ianittello",
    "email":"aianittellok@abc.net.au",
    "phone":"104-227-7754",
    "birthday":"12/27/1998",
    "company":"University of Northern Philippines",
    "passport":"Philippines",
    "destination":"Masaraway",
    "familiarFullName":"Abdul Ianittello",
    "familiarPhone":"221-165-6414",
    "status":"false",
    "profilePicturePath":"images/1.png"
  },
  {
    "firstName":"Aurlie",
    "lastName":"Edlin",
    "email":"aedlinl@wsj.com",
    "phone":"716-559-9998",
    "birthday":"8/12/1999",
    "company":"Universidade Catolica Portuguesa",
    "passport":"Portugal",
    "destination":"Outeirô",
    "familiarFullName":"Aurlie Edlin",
    "familiarPhone":"844-158-9812",
    "status":"false",
    "profilePicturePath":"images/1.png"
  },
  {
    "firstName":"Ketti",
    "lastName":"Diament",
    "email":"kdiamentm@webmd.com",
    "phone":"126-457-3398",
    "birthday":"4/2/1998",
    "company":"Technical University of Cracow",
    "passport":"Poland",
    "destination":"Bydgoszcz",
    "familiarFullName":"Ketti Diament",
    "familiarPhone":"415-362-8155",
    "status":"false",
    "profilePicturePath":"images/1.png"
  },
  {
    "firstName":"Ellie",
    "lastName":"Cokely",
    "email":"ecokelyn@twitpic.com",
    "phone":"896-104-4216",
    "birthday":"2/26/2000",
    "company":"Shanghai Lida Polytechnic Institute",
    "passport":"China",
    "destination":"Liudu",
    "familiarFullName":"Ellie Cokely",
    "familiarPhone":"887-431-5311",
    "status":"false",
    "profilePicturePath":"images/1.png"
  },
  {
    "firstName":"Rand",
    "lastName":"Treweke",
    "email":"rtrewekeo@wordpress.org",
    "phone":"929-355-2255",
    "birthday":"7/19/1997",
    "company":"Universitas Simalungun",
    "passport":"Indonesia",
    "destination":"Pesek",
    "familiarFullName":"Rand Treweke",
    "familiarPhone":"836-828-5406",
    "status":"false",
    "profilePicturePath":"images/1.png"
  },
  {
    "firstName":"Elwin",
    "lastName":"Sweedland",
    "email":"esweedlandp@dion.ne.jp",
    "phone":"122-705-4893",
    "birthday":"11/28/1999",
    "company":"Universidad Ulises Francisco Espaillat",
    "passport":"Dominican Republic",
    "destination":"Salvaleón de Higüey",
    "familiarFullName":"Elwin Sweedland",
    "familiarPhone":"596-803-8697",
    "status":"false",
    "profilePicturePath":"images/1.png"
  },
  {
    "firstName":"Falito",
    "lastName":"Jurisch",
    "email":"fjurischq@discovery.com",
    "phone":"499-826-0180",
    "birthday":"8/13/1997",
    "company":"Comilla University",
    "passport":"Comoros",
    "destination":"Ntsoudjini",
    "familiarFullName":"Falito Jurisch",
    "familiarPhone":"667-563-6438",
    "status":"false",
    "profilePicturePath":"images/1.png"
  },
  {
    "firstName":"Burty",
    "lastName":"Blaise",
    "email":"bblaiser@princeton.edu",
    "phone":"641-950-6423",
    "birthday":"12/22/1997",
    "company":"Beijing Language and Culture University",
    "passport":"China",
    "destination":"Xiaowuzhan",
    "familiarFullName":"Burty Blaise",
    "familiarPhone":"125-181-9006",
    "status":"false",
    "profilePicturePath":"images/1.png"
  },
  {
    "firstName":"Abbe",
    "lastName":"Stanbro",
    "email":"astanbros@hostgator.com",
    "phone":"794-536-0717",
    "birthday":"8/16/1999",
    "company":"Universitas Gadjah Mada",
    "passport":"Indonesia",
    "destination":"Bancak Wetan",
    "familiarFullName":"Abbe Stanbro",
    "familiarPhone":"614-697-1665",
    "status":"false",
    "profilePicturePath":"images/1.png"
  },
  {
    "firstName":"Cullie",
    "lastName":"Porcher",
    "email":"cporchert@mapquest.com",
    "phone":"280-215-5416",
    "birthday":"5/14/2000",
    "company":"Universitas Indonusa Esa Unggul",
    "passport":"Indonesia",
    "destination":"Ruteng",
    "familiarFullName":"Cullie Porcher",
    "familiarPhone":"711-590-0259",
    "status":"false",
    "profilePicturePath":"images/1.png"
  },
  {
    "firstName":"Elbertine",
    "lastName":"Lalor",
    "email":"elaloru@pagesperso-orange.fr",
    "phone":"681-150-7499",
    "birthday":"9/30/1999",
    "company":"University of Lodz",
    "passport":"Poland",
    "destination":"Sławatycze",
    "familiarFullName":"Elbertine Lalor",
    "familiarPhone":"871-984-0271",
    "status":"false",
    "profilePicturePath":"images/1.png"
  },
  {
    "firstName":"Dorry",
    "lastName":"Swidenbank",
    "email":"dswidenbankv@tuttocitta.it",
    "phone":"904-695-0122",
    "birthday":"11/16/1998",
    "company":"Texas Lutheran University",
    "passport":"United States",
    "destination":"Jacksonville",
    "familiarFullName":"Dorry Swidenbank",
    "familiarPhone":"468-513-8379",
    "status":"false",
    "profilePicturePath":"images/1.png"
  },
  {
    "firstName":"Pansy",
    "lastName":"O'Currine",
    "email":"pocurrinew@liveinternet.ru",
    "phone":"330-855-1955",
    "birthday":"11/24/1999",
    "company":"Zhengzhou Grain University",
    "passport":"China",
    "destination":"Namling",
    "familiarFullName":"Pansy O'Currine",
    "familiarPhone":"349-523-9873",
    "status":"false",
    "profilePicturePath":"images/1.png"
  },
  {
    "firstName":"Hieronymus",
    "lastName":"Darton",
    "email":"hdartonx@surveymonkey.com",
    "phone":"760-845-8785",
    "birthday":"3/26/2000",
    "company":"Universitas Kediri",
    "passport":"Indonesia",
    "destination":"Gawul",
    "familiarFullName":"Hieronymus Darton",
    "familiarPhone":"258-804-9591",
    "status":"false",
    "profilePicturePath":"images/1.png"
  },
  {
    "firstName":"Otha",
    "lastName":"Trevethan",
    "email":"otrevethany@ucoz.com",
    "phone":"249-743-5525",
    "birthday":"11/2/1998",
    "company":"Akwa Ibom State University of Technology",
    "passport":"Nigeria",
    "destination":"Iperu",
    "familiarFullName":"Otha Trevethan",
    "familiarPhone":"424-322-9450",
    "status":"false",
    "profilePicturePath":"images/1.png"
  },
  {
    "firstName":"Bernhard",
    "lastName":"Bockmaster",
    "email":"bbockmasterz@sohu.com",
    "phone":"462-231-6973",
    "birthday":"6/17/1998",
    "company":"Technical University of Czestochowa",
    "passport":"Poland",
    "destination":"Niedźwiada",
    "familiarFullName":"Bernhard Bockmaster",
    "familiarPhone":"244-148-6416",
    "status":"false",
    "profilePicturePath":"images/1.png"
  },
  {
    "firstName":"Roscoe",
    "lastName":"Codlin",
    "email":"rcodlin10@state.gov",
    "phone":"254-880-6552",
    "birthday":"11/30/1998",
    "company":"Wuhan University company of Medicine",
    "passport":"China",
    "destination":"Fengxizhai",
    "familiarFullName":"Roscoe Codlin",
    "familiarPhone":"139-149-0578",
    "status":"false",
    "profilePicturePath":"images/1.png"
  },
  {
    "firstName":"Tani",
    "lastName":"Haverson",
    "email":"thaverson11@oracle.com",
    "phone":"880-883-8553",
    "birthday":"6/22/1998",
    "company":"University of Kuopio",
    "passport":"Finland",
    "destination":"Rauma",
    "familiarFullName":"Tani Haverson",
    "familiarPhone":"307-717-8485",
    "status":"false",
    "profilePicturePath":"images/1.png"
  },
  {
    "firstName":"Yehudit",
    "lastName":"Sirmon",
    "email":"ysirmon12@un.org",
    "phone":"168-337-3937",
    "birthday":"5/30/2000",
    "company":"College of Education Ikere",
    "passport":"Nigeria",
    "destination":"Abakaliki",
    "familiarFullName":"Yehudit Sirmon",
    "familiarPhone":"721-325-8398",
    "status":"false",
    "profilePicturePath":"images/1.png"
  },
  {
    "firstName":"Grethel",
    "lastName":"Flipsen",
    "email":"gflipsen13@google.co.uk",
    "phone":"386-105-3057",
    "birthday":"10/31/1999",
    "company":"Lindenwood University",
    "passport":"United States",
    "destination":"Daytona Beach",
    "familiarFullName":"Grethel Flipsen",
    "familiarPhone":"936-878-9524",
    "status":"false",
    "profilePicturePath":"images/1.png"
  },
  {
    "firstName":"Ora",
    "lastName":"Houseman",
    "email":"ohouseman14@earthlink.net",
    "phone":"728-157-5671",
    "birthday":"6/17/1999",
    "company":"University of New Caledonia",
    "passport":"New Caledonia",
    "destination":"Mont-Dore",
    "familiarFullName":"Ora Houseman",
    "familiarPhone":"435-472-9611",
    "status":"false",
    "profilePicturePath":"images/1.png"
  },
  {
    "firstName":"Ronna",
    "lastName":"Goldes",
    "email":"rgoldes15@stanford.edu",
    "phone":"283-246-8549",
    "birthday":"8/22/1997",
    "company":"Chongqing Technology and Business University",
    "passport":"China",
    "destination":"Dingzhai",
    "familiarFullName":"Ronna Goldes",
    "familiarPhone":"276-631-1651",
    "status":"false",
    "profilePicturePath":"images/1.png"
  },
  {
    "firstName":"Marsha",
    "lastName":"Ramsden",
    "email":"mramsden16@usgs.gov",
    "phone":"236-205-2830",
    "birthday":"9/20/1999",
    "company":"Saint Ferdinand College",
    "passport":"Philippines",
    "destination":"Consolacion",
    "familiarFullName":"Marsha Ramsden",
    "familiarPhone":"808-104-9694",
    "status":"false",
    "profilePicturePath":"images/1.png"
  },
  {
    "firstName":"Ladonna",
    "lastName":"Ballchin",
    "email":"lballchin17@linkedin.com",
    "phone":"428-963-3799",
    "birthday":"6/12/1999",
    "company":"Saint Mary's University",
    "passport":"Philippines",
    "destination":"General Emilio Aguinaldo",
    "familiarFullName":"Ladonna Ballchin",
    "familiarPhone":"984-130-7002",
    "status":"false",
    "profilePicturePath":"images/1.png"
  },
  {
    "firstName":"Nikolai",
    "lastName":"O' Byrne",
    "email":"no18@home.pl",
    "phone":"154-644-2134",
    "birthday":"1/2/2000",
    "company":"Kigali Institute of Education",
    "passport":"Comoros",
    "destination":"Vouani",
    "familiarFullName":"Nikolai O' Byrne",
    "familiarPhone":"327-930-2753",
    "status":"false",
    "profilePicturePath":"images/1.png"
  },
  {
    "firstName":"Lilas",
    "lastName":"Sinkins",
    "email":"lsinkins19@ft.com",
    "phone":"177-904-5419",
    "birthday":"2/14/1999",
    "company":"Budapest Buddhist University",
    "passport":"Hungary",
    "destination":"Pécs",
    "familiarFullName":"Lilas Sinkins",
    "familiarPhone":"183-980-9452",
    "status":"false",
    "profilePicturePath":"images/1.png"
  },
  {
    "firstName":"Erda",
    "lastName":"Charer",
    "email":"echarer1a@edublogs.org",
    "phone":"828-213-1821",
    "birthday":"1/11/1999",
    "company":"Ecole d'Ingénieurs en Informatique pour l'Industrie",
    "passport":"France",
    "destination":"Bordeaux",
    "familiarFullName":"Erda Charer",
    "familiarPhone":"240-866-2135",
    "status":"false",
    "profilePicturePath":"images/1.png"
  },
  {
    "firstName":"Calla",
    "lastName":"Skeech",
    "email":"cskeech1b@infoseek.co.jp",
    "phone":"431-700-3207",
    "birthday":"5/27/1998",
    "company":"Shanghai Sipo Polytechnic",
    "passport":"China",
    "destination":"Huitong",
    "familiarFullName":"Calla Skeech",
    "familiarPhone":"245-850-6474",
    "status":"false",
    "profilePicturePath":"images/1.png"
  },
  {
    "firstName":"Tybi",
    "lastName":"Timny",
    "email":"ttimny1c@fema.gov",
    "phone":"748-707-6670",
    "birthday":"8/24/1997",
    "company":"Universidad México Internacional",
    "passport":"Kosovo",
    "destination":"Prilep",
    "familiarFullName":"Tybi Timny",
    "familiarPhone":"228-193-2273",
    "status":"false",
    "profilePicturePath":"images/1.png"
  },
  {
    "firstName":"Paulina",
    "lastName":"Napoleone",
    "email":"pnapoleone1d@toplist.cz",
    "phone":"803-572-0647",
    "birthday":"12/10/1997",
    "company":"University of Tirana",
    "passport":"Albania",
    "destination":"Hoçisht",
    "familiarFullName":"Paulina Napoleone",
    "familiarPhone":"335-672-5013",
    "status":"false",
    "profilePicturePath":"images/1.png"
  },
  {
    "firstName":"Ursula",
    "lastName":"Striker",
    "email":"ustriker1e@hubpages.com",
    "phone":"355-199-3897",
    "birthday":"7/24/1998",
    "company":"Instituto Superior de Ciênicas e Tecnologia de Moçambique",
    "passport":"Mozambique",
    "destination":"Tete",
    "familiarFullName":"Ursula Striker",
    "familiarPhone":"981-965-0382",
    "status":"false",
    "profilePicturePath":"images/1.png"
  },
  {
    "firstName":"Renie",
    "lastName":"Siddaley",
    "email":"rsiddaley1f@umich.edu",
    "phone":"430-952-3196",
    "birthday":"10/7/1997",
    "company":"Universitas Lambung Mangkurat",
    "passport":"Indonesia",
    "destination":"Sukodono",
    "familiarFullName":"Renie Siddaley",
    "familiarPhone":"588-420-4224",
    "status":"false",
    "profilePicturePath":"images/1.png"
  },
  {
    "firstName":"Nydia",
    "lastName":"Avrahamof",
    "email":"navrahamof1g@studiopress.com",
    "phone":"494-825-2420",
    "birthday":"4/20/1999",
    "company":"Universitas Islam Syekh-Yusuf ",
    "passport":"Indonesia",
    "destination":"Cipicung Timur",
    "familiarFullName":"Nydia Avrahamof",
    "familiarPhone":"886-223-1889",
    "status":"false",
    "profilePicturePath":"images/1.png"
  },
  {
    "firstName":"Morrie",
    "lastName":"Gilffilland",
    "email":"mgilffilland1h@slideshare.net",
    "phone":"759-754-4005",
    "birthday":"2/6/2000",
    "company":"Universitas Gadjah Mada",
    "passport":"Indonesia",
    "destination":"Nunbaundelha",
    "familiarFullName":"Morrie Gilffilland",
    "familiarPhone":"819-206-4431",
    "status":"false",
    "profilePicturePath":"images/1.png"
  },
  {
    "firstName":"Brian",
    "lastName":"Blackney",
    "email":"bblackney1i@addthis.com",
    "phone":"212-660-5982",
    "birthday":"7/5/1998",
    "company":"New Jersey City University",
    "passport":"United States",
    "destination":"Jamaica",
    "familiarFullName":"Brian Blackney",
    "familiarPhone":"605-502-1486",
    "status":"false",
    "profilePicturePath":"images/1.png"
  },
  {
    "firstName":"Rheta",
    "lastName":"Fladgate",
    "email":"rfladgate1j@about.com",
    "phone":"357-936-5193",
    "birthday":"4/27/2000",
    "company":"Universidade Estadual Sudoeste da Bahia",
    "passport":"Brazil",
    "destination":"Carangola",
    "familiarFullName":"Rheta Fladgate",
    "familiarPhone":"771-970-6440",
    "status":"false",
    "profilePicturePath":"images/1.png"
  },
  {
    "firstName":"Ansley",
    "lastName":"Evins",
    "email":"aevins1k@bandcamp.com",
    "phone":"306-853-5606",
    "birthday":"10/12/1998",
    "company":"Chengdu Institute of Sichuan International Studies University",
    "passport":"China",
    "destination":"Baiyinnuole",
    "familiarFullName":"Ansley Evins",
    "familiarPhone":"528-473-6193",
    "status":"false",
    "profilePicturePath":"images/1.png"
  },
  {
    "firstName":"Shell",
    "lastName":"Piff",
    "email":"spiff1l@prnewswire.com",
    "phone":"205-980-6902",
    "birthday":"10/30/1999",
    "company":"Universidad Nacional de Cuyo",
    "passport":"Argentina",
    "destination":"Fray Luis A. Beltrán",
    "familiarFullName":"Shell Piff",
    "familiarPhone":"486-800-7958",
    "status":"false",
    "profilePicturePath":"images/1.png"
  },
  {
    "firstName":"Valenka",
    "lastName":"de Clercq",
    "email":"vde1m@earthlink.net",
    "phone":"316-890-0370",
    "birthday":"9/15/1997",
    "company":"Pontificia Universidade Católica do Paraná",
    "passport":"Brazil",
    "destination":"Corrego Grande",
    "familiarFullName":"Valenka de Clercq",
    "familiarPhone":"885-592-0680",
    "status":"false",
    "profilePicturePath":"images/1.png"
  },
  {
    "firstName":"Zia",
    "lastName":"Ryott",
    "email":"zryott1n@fda.gov",
    "phone":"428-138-0881",
    "birthday":"3/28/1999",
    "company":"Samara State Agricultural Academy",
    "passport":"Russia",
    "destination":"Tver",
    "familiarFullName":"Zia Ryott",
    "familiarPhone":"188-884-3107",
    "status":"false",
    "profilePicturePath":"images/1.png"
  },
  {
    "firstName":"Mathew",
    "lastName":"Brabham",
    "email":"mbrabham1o@github.com",
    "phone":"846-302-0501",
    "birthday":"6/4/1998",
    "company":"Université du Maine",
    "passport":"France",
    "destination":"Marseille",
    "familiarFullName":"Mathew Brabham",
    "familiarPhone":"730-248-0792",
    "status":"false",
    "profilePicturePath":"images/1.png"
  },
  {
    "firstName":"Winny",
    "lastName":"Purver",
    "email":"wpurver1p@amazonaws.com",
    "phone":"523-126-1166",
    "birthday":"5/16/2000",
    "company":"Agricultural University of Georgia",
    "passport":"Georgia",
    "destination":"T’et’ri Tsqaro",
    "familiarFullName":"Winny Purver",
    "familiarPhone":"426-216-8788",
    "status":"false",
    "profilePicturePath":"images/1.png"
  },
  {
    "firstName":"Joly",
    "lastName":"Winsor",
    "email":"jwinsor1q@home.pl",
    "phone":"337-696-3549",
    "birthday":"1/4/2000",
    "company":"Shanghai Ocean University",
    "passport":"China",
    "destination":"Hekou",
    "familiarFullName":"Joly Winsor",
    "familiarPhone":"178-298-4296",
    "status":"false",
    "profilePicturePath":"images/1.png"
  },
  {
    "firstName":"Enrica",
    "lastName":"Passie",
    "email":"epassie1r@de.vu",
    "phone":"933-845-7154",
    "birthday":"11/2/1997",
    "company":"Escola Superior de Artes e Design",
    "passport":"Portugal",
    "destination":"Oliveira de Baixo",
    "familiarFullName":"Enrica Passie",
    "familiarPhone":"702-381-4436",
    "status":"false",
    "profilePicturePath":"images/1.png"
  },
  {
    "firstName":"Hasty",
    "lastName":"Hainey`",
    "email":"hhainey1s@jugem.jp",
    "phone":"768-689-6074",
    "birthday":"6/16/1999",
    "company":"Instituto Politécnico do Cávado e do Ave",
    "passport":"Portugal",
    "destination":"Barqueiro",
    "familiarFullName":"Hasty Hainey`",
    "familiarPhone":"791-362-8821",
    "status":"false",
    "profilePicturePath":"images/1.png"
  },
  {
    "firstName":"Ethelda",
    "lastName":"Bassilashvili",
    "email":"ebassilashvili1t@typepad.com",
    "phone":"604-218-5306",
    "birthday":"3/17/2000",
    "company":"Universitas Muhammadiyah Magelang",
    "passport":"Indonesia",
    "destination":"Nggelok",
    "familiarFullName":"Ethelda Bassilashvili",
    "familiarPhone":"532-624-4023",
    "status":"false",
    "profilePicturePath":"images/1.png"
  },
  {
    "firstName":"Candida",
    "lastName":"Rigler",
    "email":"crigler1u@examiner.com",
    "phone":"842-875-9437",
    "birthday":"6/29/1997",
    "company":"University of Aden",
    "passport":"Yemen",
    "destination":"Banī an Nahārī",
    "familiarFullName":"Candida Rigler",
    "familiarPhone":"976-356-5957",
    "status":"false",
    "profilePicturePath":"images/1.png"
  },
  {
    "firstName":"Janetta",
    "lastName":"Scimoni",
    "email":"jscimoni1v@elpais.com",
    "phone":"709-369-2773",
    "birthday":"2/19/1999",
    "company":"Universidad de Holguín",
    "passport":"Cuba",
    "destination":"Jesús Menéndez",
    "familiarFullName":"Janetta Scimoni",
    "familiarPhone":"364-631-2574",
    "status":"false",
    "profilePicturePath":"images/1.png"
  },
  {
    "firstName":"Keen",
    "lastName":"Rake",
    "email":"krake1w@pbs.org",
    "phone":"146-611-3200",
    "birthday":"11/11/1997",
    "company":"University for Information Science and Technology  \"St. Paul The Apostle\" ",
    "passport":"Macedonia",
    "destination":"Липково",
    "familiarFullName":"Keen Rake",
    "familiarPhone":"983-571-7113",
    "status":"false",
    "profilePicturePath":"images/1.png"
  },
  {
    "firstName":"Michel",
    "lastName":"Kingsly",
    "email":"mkingsly1x@digg.com",
    "phone":"862-944-0527",
    "birthday":"12/3/1998",
    "company":"Universiti Teknologi Malaysia",
    "passport":"Malaysia",
    "destination":"Seremban",
    "familiarFullName":"Michel Kingsly",
    "familiarPhone":"985-332-4945",
    "status":"false",
    "profilePicturePath":"images/1.png"
  },
  {
    "firstName":"Gwendolin",
    "lastName":"Wisam",
    "email":"gwisam1y@exblog.jp",
    "phone":"842-457-6942",
    "birthday":"10/25/1997",
    "company":"Dnepropetrovsk National University of Railway Transport",
    "passport":"Ukraine",
    "destination":"Pnikut",
    "familiarFullName":"Gwendolin Wisam",
    "familiarPhone":"535-748-9651",
    "status":"false",
    "profilePicturePath":"images/1.png"
  },
  {
    "firstName":"Wanids",
    "lastName":"Pratton",
    "email":"wpratton1z@a8.net",
    "phone":"373-779-6613",
    "birthday":"1/7/1998",
    "company":"University of Liberia",
    "passport":"Liberia",
    "destination":"Harper",
    "familiarFullName":"Wanids Pratton",
    "familiarPhone":"917-413-2733",
    "status":"false",
    "profilePicturePath":"images/1.png"
  },
  {
    "firstName":"Aarika",
    "lastName":"Greenway",
    "email":"agreenway20@accuweather.com",
    "phone":"902-356-7634",
    "birthday":"4/27/2000",
    "company":"Guangdong Polytechnic Normal University",
    "passport":"China",
    "destination":"Shazikou",
    "familiarFullName":"Aarika Greenway",
    "familiarPhone":"672-620-7041",
    "status":"false",
    "profilePicturePath":"images/1.png"
  },
  {
    "firstName":"Anjanette",
    "lastName":"Mathouse",
    "email":"amathouse21@reference.com",
    "phone":"453-853-7796",
    "birthday":"6/17/1999",
    "company":"Nanjing University of Chemical Technology",
    "passport":"China",
    "destination":"Lijia",
    "familiarFullName":"Anjanette Mathouse",
    "familiarPhone":"146-690-3372",
    "status":"false",
    "profilePicturePath":"images/1.png"
  },
  {
    "firstName":"Gwynne",
    "lastName":"Bould",
    "email":"gbould22@yahoo.co.jp",
    "phone":"799-291-5245",
    "birthday":"9/30/1997",
    "company":"European Management Center Paris",
    "passport":"France",
    "destination":"Nantes",
    "familiarFullName":"Gwynne Bould",
    "familiarPhone":"223-503-3988",
    "status":"false",
    "profilePicturePath":"images/1.png"
  },
  {
    "firstName":"Giustina",
    "lastName":"Tingey",
    "email":"gtingey23@alibaba.com",
    "phone":"616-392-9459",
    "birthday":"7/23/1998",
    "company":"Universidade Tiradentes",
    "passport":"Brazil",
    "destination":"Carpina",
    "familiarFullName":"Giustina Tingey",
    "familiarPhone":"987-946-5707",
    "status":"false",
    "profilePicturePath":"images/1.png"
  },
  {
    "firstName":"Vlad",
    "lastName":"Donnelly",
    "email":"vdonnelly24@ucoz.ru",
    "phone":"468-592-4489",
    "birthday":"3/9/1998",
    "company":"Ivanovo State University of Chemistry and Technology",
    "passport":"Russia",
    "destination":"Zhukovo",
    "familiarFullName":"Vlad Donnelly",
    "familiarPhone":"528-243-4160",
    "status":"false",
    "profilePicturePath":"images/1.png"
  },
  {
    "firstName":"Olag",
    "lastName":"Hacard",
    "email":"ohacard25@usnews.com",
    "phone":"145-282-4209",
    "birthday":"5/3/1999",
    "company":"Instituto Politécnico de Castelo Branco",
    "passport":"Portugal",
    "destination":"Maiorca",
    "familiarFullName":"Olag Hacard",
    "familiarPhone":"870-103-5251",
    "status":"false",
    "profilePicturePath":"images/1.png"
  },
  {
    "firstName":"Lucian",
    "lastName":"Vedenisov",
    "email":"lvedenisov26@ihg.com",
    "phone":"222-497-5866",
    "birthday":"7/8/1998",
    "company":"University of Paisley",
    "passport":"Isle of Man",
    "destination":"Port Erin",
    "familiarFullName":"Lucian Vedenisov",
    "familiarPhone":"257-297-8433",
    "status":"false",
    "profilePicturePath":"images/1.png"
  },
  {
    "firstName":"Sheff",
    "lastName":"Cotsford",
    "email":"scotsford27@bbb.org",
    "phone":"416-782-9153",
    "birthday":"8/7/1999",
    "company":"Higher company of Economics",
    "passport":"Russia",
    "destination":"Severo-Zadonsk",
    "familiarFullName":"Sheff Cotsford",
    "familiarPhone":"590-295-3936",
    "status":"false",
    "profilePicturePath":"images/1.png"
  },
  {
    "firstName":"Bil",
    "lastName":"Teck",
    "email":"bteck28@webmd.com",
    "phone":"321-380-4545",
    "birthday":"1/19/1999",
    "company":"Universidad APEC",
    "passport":"Dominican Republic",
    "destination":"Jicomé",
    "familiarFullName":"Bil Teck",
    "familiarPhone":"667-179-0064",
    "status":"false",
    "profilePicturePath":"images/1.png"
  },
  {
    "firstName":"Marrissa",
    "lastName":"Skough",
    "email":"mskough29@tamu.edu",
    "phone":"232-834-0464",
    "birthday":"8/9/1999",
    "company":"Ulaanbaatar University",
    "passport":"Mongolia",
    "destination":"Bayanhoshuu",
    "familiarFullName":"Marrissa Skough",
    "familiarPhone":"651-925-5278",
    "status":"false",
    "profilePicturePath":"images/1.png"
  },
  {
    "firstName":"Siana",
    "lastName":"O'Spillane",
    "email":"sospillane2a@naver.com",
    "phone":"704-966-0376",
    "birthday":"5/11/1999",
    "company":"Samara State University of Teacher Training",
    "passport":"Russia",
    "destination":"Liski",
    "familiarFullName":"Siana O'Spillane",
    "familiarPhone":"637-902-7997",
    "status":"false",
    "profilePicturePath":"images/1.png"
  },
  {
    "firstName":"Gusta",
    "lastName":"Kinnear",
    "email":"gkinnear2b@github.io",
    "phone":"619-547-8903",
    "birthday":"11/11/1999",
    "company":"Civil Aviation University of China",
    "passport":"China",
    "destination":"Xiangcheng",
    "familiarFullName":"Gusta Kinnear",
    "familiarPhone":"941-334-5703",
    "status":"false",
    "profilePicturePath":"images/1.png"
  },
  {
    "firstName":"Germaine",
    "lastName":"Maskell",
    "email":"gmaskell2c@chronoengine.com",
    "phone":"518-866-2420",
    "birthday":"7/14/1999",
    "company":"Universidad La Republica",
    "passport":"Chile",
    "destination":"Puerto Varas",
    "familiarFullName":"Germaine Maskell",
    "familiarPhone":"421-478-3381",
    "status":"false",
    "profilePicturePath":"images/1.png"
  },
  {
    "firstName":"Marina",
    "lastName":"D'Enrico",
    "email":"mdenrico2d@stanford.edu",
    "phone":"828-953-9367",
    "birthday":"3/18/1998",
    "company":"Universidade de Santa Cruz do Sul",
    "passport":"Brazil",
    "destination":"Jardim",
    "familiarFullName":"Marina D'Enrico",
    "familiarPhone":"494-274-7440",
    "status":"false",
    "profilePicturePath":"images/1.png"
  },
  {
    "firstName":"Analiese",
    "lastName":"O'Spellissey",
    "email":"aospellissey2e@ameblo.jp",
    "phone":"619-851-7971",
    "birthday":"10/11/1997",
    "company":"Universidad Nacional Autónoma de Honduras",
    "passport":"Honduras",
    "destination":"Silca",
    "familiarFullName":"Analiese O'Spellissey",
    "familiarPhone":"802-773-1710",
    "status":"false",
    "profilePicturePath":"images/1.png"
  },
  {
    "firstName":"Alisha",
    "lastName":"Elloy",
    "email":"aelloy2f@disqus.com",
    "phone":"131-439-4944",
    "birthday":"12/7/1998",
    "company":"Jimei University",
    "passport":"China",
    "destination":"Xiangying",
    "familiarFullName":"Alisha Elloy",
    "familiarPhone":"175-117-2393",
    "status":"false",
    "profilePicturePath":"images/1.png"
  },
  {
    "firstName":"Giffer",
    "lastName":"Ordelt",
    "email":"gordelt2g@techcrunch.com",
    "phone":"930-281-1469",
    "birthday":"5/13/2000",
    "company":"University of Luxemburg",
    "passport":"Luxembourg",
    "destination":"Wincrange",
    "familiarFullName":"Giffer Ordelt",
    "familiarPhone":"614-173-2463",
    "status":"false",
    "profilePicturePath":"images/1.png"
  },
  {
    "firstName":"Dido",
    "lastName":"Woolacott",
    "email":"dwoolacott2h@soundcloud.com",
    "phone":"298-436-4193",
    "birthday":"11/12/1999",
    "company":"Universidad de Lima",
    "passport":"Peru",
    "destination":"Tomepampa",
    "familiarFullName":"Dido Woolacott",
    "familiarPhone":"506-168-2707",
    "status":"false",
    "profilePicturePath":"images/1.png"
  },
  {
    "firstName":"Marylin",
    "lastName":"Godthaab",
    "email":"mgodthaab2i@soup.io",
    "phone":"826-271-7347",
    "birthday":"3/30/2000",
    "company":"Dalian Polytechnic University",
    "passport":"China",
    "destination":"Aimin",
    "familiarFullName":"Marylin Godthaab",
    "familiarPhone":"383-166-9360",
    "status":"false",
    "profilePicturePath":"images/1.png"
  },
  {
    "firstName":"Glynn",
    "lastName":"Kleinber",
    "email":"gkleinber2j@ed.gov",
    "phone":"779-891-8846",
    "birthday":"10/16/1998",
    "company":"Medical Academy in Bialystok",
    "passport":"Poland",
    "destination":"Łodygowice",
    "familiarFullName":"Glynn Kleinber",
    "familiarPhone":"335-927-3844",
    "status":"false",
    "profilePicturePath":"images/1.png"
  },
  {
    "firstName":"Pepe",
    "lastName":"Bleibaum",
    "email":"pbleibaum2k@psu.edu",
    "phone":"280-162-5580",
    "birthday":"2/26/1999",
    "company":"Yunnan University",
    "passport":"China",
    "destination":"Chengxiang",
    "familiarFullName":"Pepe Bleibaum",
    "familiarPhone":"415-967-5165",
    "status":"false",
    "profilePicturePath":"images/1.png"
  },
  {
    "firstName":"Ranique",
    "lastName":"De Santos",
    "email":"rde2l@furl.net",
    "phone":"247-306-7861",
    "birthday":"10/29/1999",
    "company":"Cavendish University",
    "passport":"Zambia",
    "destination":"Kitwe",
    "familiarFullName":"Ranique De Santos",
    "familiarPhone":"973-181-2554",
    "status":"false",
    "profilePicturePath":"images/1.png"
  },
  {
    "firstName":"Fraser",
    "lastName":"Muckleston",
    "email":"fmuckleston2m@youku.com",
    "phone":"933-532-6046",
    "birthday":"1/5/2000",
    "company":"Holy Angel University",
    "passport":"Philippines",
    "destination":"Taytay",
    "familiarFullName":"Fraser Muckleston",
    "familiarPhone":"744-280-1829",
    "status":"false",
    "profilePicturePath":"images/1.png"
  },
  {
    "firstName":"Jennie",
    "lastName":"Charrington",
    "email":"jcharrington2n@samsung.com",
    "phone":"557-167-4321",
    "birthday":"3/27/2000",
    "company":"Hebei Normal University",
    "passport":"China",
    "destination":"Dabagou",
    "familiarFullName":"Jennie Charrington",
    "familiarPhone":"142-232-5144",
    "status":"false",
    "profilePicturePath":"images/1.png"
  },
  {
    "firstName":"Harli",
    "lastName":"Andreopolos",
    "email":"handreopolos2o@last.fm",
    "phone":"566-915-7832",
    "birthday":"2/16/1998",
    "company":"Instituto Politécnico de Santarém",
    "passport":"Portugal",
    "destination":"Calvário",
    "familiarFullName":"Harli Andreopolos",
    "familiarPhone":"556-150-8474",
    "status":"false",
    "profilePicturePath":"images/1.png"
  },
  {
    "firstName":"Janine",
    "lastName":"Chiddy",
    "email":"jchiddy2p@eepurl.com",
    "phone":"314-106-8714",
    "birthday":"10/2/1997",
    "company":"California Western company of Law",
    "passport":"United States",
    "destination":"Saint Louis",
    "familiarFullName":"Janine Chiddy",
    "familiarPhone":"426-336-5181",
    "status":"false",
    "profilePicturePath":"images/1.png"
  },
  {
    "firstName":"Wendeline",
    "lastName":"Thew",
    "email":"wthew2q@ftc.gov",
    "phone":"479-787-9024",
    "birthday":"5/10/2000",
    "company":"Politécnico Columbiano \"Jaime Isaza Cadavid\"",
    "passport":"Colombia",
    "destination":"Miranda",
    "familiarFullName":"Wendeline Thew",
    "familiarPhone":"131-133-4750",
    "status":"false",
    "profilePicturePath":"images/1.png"
  },
  {
    "firstName":"Hailee",
    "lastName":"Cordeux",
    "email":"hcordeux2r@omniture.com",
    "phone":"143-256-0037",
    "birthday":"7/24/1997",
    "company":"Malaspina University College",
    "passport":"Canada",
    "destination":"Sylvan Lake",
    "familiarFullName":"Hailee Cordeux",
    "familiarPhone":"831-253-9332",
    "status":"false",
    "profilePicturePath":"images/1.png"
  }
]